README.txt
setup.py
collective/__init__.py
collective.recipe.realpath.egg-info/PKG-INFO
collective.recipe.realpath.egg-info/SOURCES.txt
collective.recipe.realpath.egg-info/dependency_links.txt
collective.recipe.realpath.egg-info/entry_points.txt
collective.recipe.realpath.egg-info/namespace_packages.txt
collective.recipe.realpath.egg-info/not-zip-safe
collective.recipe.realpath.egg-info/requires.txt
collective.recipe.realpath.egg-info/top_level.txt
collective/recipe/__init__.py
collective/recipe/realpath/README.txt
collective/recipe/realpath/__init__.py
collective/recipe/realpath/tests/__init__.py
collective/recipe/realpath/tests/test_docs.py
docs/COPYING.txt