Metadata-Version: 1.0
Name: collective.recipe.realpath
Version: 0.1
Summary: Buildout recipe normalizes directory/path options.
Home-page: http://svn.plone.org/svn/collective
Author: Sean Upton
Author-email: sean.upton@hsc.utah.edu
License: MIT
Platform: UNKNOWN
Classifier: Programming Language :: Python
Classifier: Framework :: Buildout
Classifier: Intended Audience :: Developers
Classifier: Topic :: Software Development :: Build Tools
Classifier: License :: OSI Approved :: MIT License
